mr_sim/__init__.py
mr_sim/base.py
mr_sim/models.py
mr_sim/pressure.py
mr_sim/shapes.py
mr_sim/types.py
mr_sim-1.0.1.dist-info/LICENSE
mr_sim-1.0.1.dist-info/METADATA
mr_sim-1.0.1.dist-info/WHEEL
mr_sim-1.0.1.dist-info/top_level.txt
mr_sim-1.0.1.dist-info/RECORD
