Metadata-Version: 2.1
Name: mr-sim
Version: 1.0.1
Summary: A package for the simulation of abrasive material removal processes.
Home-page: https://github.com/CameronDevine/mr_sim
Author: Cameron Devine
Author-email: camdev@uw.edu
License: UNKNOWN
Platform: UNKNOWN
Classifier: Intended Audience :: Manufacturing
Classifier: Intended Audience :: Science/Research
Classifier: License :: OSI Approved :: BSD License
Classifier: Operating System :: OS Independent
Classifier: Topic :: Scientific/Engineering
Classifier: Programming Language :: Python :: 3 :: Only
Classifier: Programming Language :: Python :: 3.4
Classifier: Programming Language :: Python :: 3.5
Classifier: Programming Language :: Python :: 3.6
Classifier: Programming Language :: Python :: 3.7
Classifier: Programming Language :: Python :: 3.8
Requires-Python: >=3.4
Requires-Dist: numpy
Requires-Dist: scipy
